csv_reconcile/__init__.py
csv_reconcile/__main__.py
csv_reconcile/db.py
csv_reconcile/default_settings.py
csv_reconcile/extend.py
csv_reconcile/initdb.py
csv_reconcile/preview.py
csv_reconcile/schema.sql
csv_reconcile/score.py
csv_reconcile/scorer.py
csv_reconcile_dice/__init__.py
csv_reconcile_dice/cutils.c
csv_reconcile_dice/cutils.pyx
csv_reconcile_dice/utils.py
csv_reconcile-0.3.0.dist-info/entry_points.txt
csv_reconcile-0.3.0.dist-info/LICENSE
csv_reconcile-0.3.0.dist-info/WHEEL
csv_reconcile-0.3.0.dist-info/METADATA
csv_reconcile-0.3.0.dist-info/RECORD
