Metadata-Version: 2.1
Name: csv-reconcile
Version: 0.3.0
Summary: OpenRefine reconciliation service backed by csv resource
Home-page: https://github.com/gitonthescene/csv-reconcile
License: MIT
Keywords: OpenRefine,reconcile,fuzzy search
Author: Douglas Mennella
Author-email: trx2358-pypi@yahoo.com
Requires-Python: >=3.7,<4.0
Classifier: License :: OSI Approved :: MIT License
Classifier: Programming Language :: Python :: 3
Classifier: Programming Language :: Python :: 3.10
Classifier: Programming Language :: Python :: 3.7
Classifier: Programming Language :: Python :: 3.8
Classifier: Programming Language :: Python :: 3.9
Requires-Dist: cython (>=0.29.21,<0.30.0)
Requires-Dist: flask (>=2.0,<3.0)
Requires-Dist: flask-cors (>=3.0.10,<4.0.0)
Requires-Dist: importlib_metadata (>=4.5.0,<5.0.0); python_version < "3.10"
Requires-Dist: normality (>=2.1.1,<3.0.0)
Project-URL: Repository, https://github.com/gitonthescene/csv-reconcile
